{
  "schema_version": "1",
  "open_source": true,
  "model_name": "poker44_gen11lgbm",
  "model_version": "11.0",
  "framework": "python-lightgbm",
  "license": "MIT",
  "repo_url": "https://github.com/tomkaba/poker44-miner-gen11lgbm",
  "repo_commit": "0cb88e890fee2540e0dbc2252122893454452291",
  "inference_mode": "remote",
  "training_data_statement": "No validator-private data used.",
  "data_attestation": "This miner does not train on validator-private human data.",
  "private_data_attestation": "This miner does not train on validator-private human data.",
  "implementation_files": [
    "models/benchmark_lgbm_model.pkl",
    "models/benchmark_lgbm_profile.json",
    "neurons/miner.py",
    "poker44/base/miner.py",
    "poker44/base/neuron.py",
    "poker44/miner_heuristics.py",
    "poker44/utils/config.py",
    "poker44/utils/misc.py",
    "poker44/utils/model_manifest.py",
    "poker44/validator/synapse.py"
  ],
  "implementation_sha256": "ab6920e790204c88b49fafbb839984b6badc6e3d82336b1fe914b3189753d0dd",
  "notes": "Gen11lgbm LightGBM chunk scorer."
}
